{"files":[{"name":"add_shortcur.reg","size":"0.73KB","length":751,"children":null},{"name":"common","size":"4.00KB","length":4096,"children":[{"name":"jiami.js","size":"0.97KB","length":998,"children":null},{"name":"uuid.js","size":"0.48KB","length":491,"children":null}]},{"name":"data.json","size":"2.09KB","length":2144,"children":null},{"name":"flutter.txt","size":"1.23KB","length":1263,"children":null},{"name":"img","size":"4.00KB","length":4096,"children":[{"name":"fs","size":"4.00KB","length":4096,"children":[{"name":"readme.png","size":"46.41KB","length":47523,"children":null}]}]},{"name":"init.gradle","size":"3.50KB","length":3584,"children":null},{"name":"modao","size":"4.00KB","length":4096,"children":[{"name":"upgrade.html","size":"0.41KB","length":420,"children":null}]},{"name":"mogai","size":"4.00KB","length":4096,"children":[{"name":"alert.js","size":"0.02KB","length":18,"children":null},{"name":"blog.csdn.net.js","size":"0.11KB","length":113,"children":null}]},{"name":"mogai.json","size":"0.17KB","length":177,"children":null},{"name":"motuo","size":"4.00KB","length":4096,"children":[{"name":"login.js","size":"2.27KB","length":2324,"children":null},{"name":"ssr.js","size":"1.43KB","length":1469,"children":null},{"name":"sys.json","size":"0.70KB","length":713,"children":null},{"name":"test.js","size":"0.17KB","length":169,"children":null}]},{"name":"ok.txt","size":"0.04KB","length":36,"children":null},{"name":"page.json","size":"0.38KB","length":391,"children":null},{"name":"readme.md","size":"0.07KB","length":72,"children":null},{"name":"static","size":"4.00KB","length":4096,"children":[{"name":"main.ts","size":"2.56KB","length":2622,"children":null},{"name":"style.scss","size":"0.39KB","length":403,"children":null},{"name":"tpl.htm","size":"0.29KB","length":298,"children":null}]}],"time":"2022-10-22 09:41:45"}